{
  "2308-08746": {
    "title": "SurgicalSAM: Efficient Class Promptable Surgical Instrument Segmentation",
    "authors": [
      "Wenxi Yue",
      "Jing Zhang",
      "Kun Hu",
      "Yong Xia",
      "Jiebo Luo",
      "Zhiyong Wang"
    ],
    "publication_date": "2023-08-17",
    "venue": "AAAI Conference on Artificial Intelligence",
    "semantic_scholar_id": "2cfbeb0c2a0c268773e3b952f022aada9cfd0538",
    "corpus_id": 261031148,
    "category": "Computer Science"
  },
  "2306-09244": {
    "title": "Text Promptable Surgical Instrument Segmentation with Vision-Language Models",
    "authors": [
      "Zijian Zhou",
      "Oluwatosin O. Alabi",
      "Meng Wei",
      "Tom Kamiel Magda Vercauteren",
      "Miaojing Shi"
    ],
    "publication_date": "2023-06-15",
    "venue": "Neural Information Processing Systems",
    "semantic_scholar_id": "cd51dda4f02b2294a0b61385862d4ed091076755",
    "corpus_id": 259165099,
    "category": "Computer Science"
  },
  "2306-00968": {
    "title": "GRES: Generalized Referring Expression Segmentation",
    "authors": [
      "Chang Liu",
      "Henghui Ding",
      "Xudong Jiang"
    ],
    "publication_date": "2023-06-01",
    "venue": "Computer Vision and Pattern Recognition",
    "semantic_scholar_id": "1ec4bc98fafa8d338f676f7a1b1b1131e8ca978e",
    "corpus_id": 258999674,
    "category": "Computer Science"
  },
  "2304-02643": {
    "title": "Segment Anything",
    "authors": [
      "A. Kirillov",
      "Eric Mintun",
      "Nikhila Ravi",
      "Hanzi Mao",
      "Chloé Rolland",
      "Laura Gustafson",
      "Tete Xiao",
      "Spencer Whitehead",
      "A. Berg",
      "Wan-Yen Lo",
      "Piotr Dollár",
      "Ross B. Girshick"
    ],
    "publication_date": "2023-04-05",
    "venue": "IEEE International Conference on Computer Vision",
    "semantic_scholar_id": "7470a1702c8c86e6f28d32cfa315381150102f5b",
    "corpus_id": 257952310,
    "category": "Computer Science"
  },
  "2303-09514": {
    "title": "MATIS: Masked-Attention Transformers for Surgical Instrument Segmentation",
    "authors": [
      "Nicolás Ayobi",
      "Alejandra P'erez-Rond'on",
      "Santiago A. Rodr'iguez",
      "Pablo Arbel'aez"
    ],
    "publication_date": "2023-03-16",
    "venue": "IEEE International Symposium on Biomedical Imaging",
    "semantic_scholar_id": "3faaca5bfafe11f41617bb28199528772f0e254f",
    "corpus_id": 257557473,
    "category": "Computer Science"
  },
  "2211-16200": {
    "title": "From Forks to Forceps: A New Framework for Instance Segmentation of Surgical Instruments",
    "authors": [
      "Britty Baby",
      "Daksh Thapar",
      "Mustafa Chasmai",
      "Tamajit Banerjee",
      "Kunal Dargan",
      "A. Suri",
      "Subhashis Banerjee",
      "Chetan Arora"
    ],
    "publication_date": "2022-11-26",
    "venue": "IEEE Workshop/Winter Conference on Applications of Computer Vision",
    "semantic_scholar_id": "c4c2ea3922ed963085e4bd3cd168c7b09f45f946",
    "corpus_id": 254070010,
    "category": "Computer Science"
  },
  "2209-09554": {
    "title": "Towards Robust Referring Image Segmentation",
    "authors": [
      "Jianzong Wu",
      "Xiangtai Li",
      "Xia Li",
      "Henghui Ding",
      "Yu Tong",
      "Dacheng Tao"
    ],
    "publication_date": "2022-09-20",
    "venue": "arXiv.org",
    "semantic_scholar_id": "f8e72fb047b60bae943d745621c5f1c085df7d72",
    "corpus_id": 252383577,
    "category": "Computer Science"
  },
  "2202-08453": {
    "title": "TraSeTR: Track-to-Segment Transformer with Contrastive Query for Instance-level Instrument Segmentation in Robotic Surgery",
    "authors": [
      "Zixu Zhao",
      "Yueming Jin",
      "P. Heng"
    ],
    "publication_date": "2022-02-17",
    "venue": "IEEE International Conference on Robotics and Automation",
    "semantic_scholar_id": "01c6d124fc66250da17a9fbf20ce46c2861b9b25",
    "corpus_id": 246904863,
    "category": "Computer Science"
  },
  "2112-02244": {
    "title": "LAVT: Language-Aware Vision Transformer for Referring Image Segmentation",
    "authors": [
      "Zhao Yang",
      "Jiaqi Wang",
      "Yansong Tang",
      "Kai Chen",
      "Hengshuang Zhao",
      "Philip H. S. Torr"
    ],
    "publication_date": "2021-12-04",
    "venue": "Computer Vision and Pattern Recognition",
    "semantic_scholar_id": "ca1d5aa8f63707931692bf6a62642becf928c1fa",
    "corpus_id": 244909191,
    "category": "Computer Science"
  },
  "2112-01527": {
    "title": "Masked-attention Mask Transformer for Universal Image Segmentation",
    "authors": [
      "Bowen Cheng",
      "Ishan Misra",
      "A. Schwing",
      "Alexander Kirillov",
      "Rohit Girdhar"
    ],
    "publication_date": "2021-12-02",
    "venue": "Computer Vision and Pattern Recognition",
    "semantic_scholar_id": "658a017302d29e4acf4ca789cb5d9f27983717ff",
    "corpus_id": 244799297,
    "category": "Computer Science"
  },
  "2108-05565": {
    "title": "Vision-Language Transformer and Query Generation for Referring Segmentation",
    "authors": [
      "Henghui Ding",
      "Chang Liu",
      "Suchen Wang",
      "Xudong Jiang"
    ],
    "publication_date": "2021-08-12",
    "venue": "IEEE International Conference on Computer Vision",
    "semantic_scholar_id": "367a5169efb790a15bcc1afcb0164b32740b751a",
    "corpus_id": 236987044,
    "category": "Computer Science"
  },
  "2105-01839": {
    "title": "Encoder Fusion Network with Co-Attention Embedding for Referring Image Segmentation",
    "authors": [
      "Guang Feng",
      "Zhiwei Hu",
      "Lihe Zhang",
      "Huchuan Lu"
    ],
    "publication_date": "2021-05-05",
    "venue": "Computer Vision and Pattern Recognition",
    "semantic_scholar_id": "102cbf1eb78b2c0bdb998ac514dcbae27143c85a",
    "corpus_id": 233740054,
    "category": "Computer Science"
  },
  "2103-00020": {
    "title": "Learning Transferable Visual Models From Natural Language Supervision",
    "authors": [
      "Alec Radford",
      "Jong Wook Kim",
      "Chris Hallacy",
      "A. Ramesh",
      "Gabriel Goh",
      "Sandhini Agarwal",
      "Girish Sastry",
      "Amanda Askell",
      "Pamela Mishkin",
      "Jack Clark",
      "Gretchen Krueger",
      "I. Sutskever"
    ],
    "publication_date": "2021-02-26",
    "venue": "International Conference on Machine Learning",
    "semantic_scholar_id": "6f870f7f02a8c59c3e23f407f3ef00dd1dcf8fc4",
    "corpus_id": 231591445,
    "category": "Computer Science"
  },
  "2010-11929": {
    "title": "An Image is Worth 16x16 Words: Transformers for Image Recognition at Scale",
    "authors": [
      "Alexey Dosovitskiy",
      "Lucas Beyer",
      "Alexander Kolesnikov",
      "Dirk Weissenborn",
      "Xiaohua Zhai",
      "Thomas Unterthiner",
      "Mostafa Dehghani",
      "M. Minderer",
      "G. Heigold",
      "S. Gelly",
      "Jakob Uszkoreit",
      "N. Houlsby"
    ],
    "publication_date": "2020-10-22",
    "venue": "International Conference on Learning Representations",
    "semantic_scholar_id": "268d347e8a55b5eb82fb5e7d2f800e33c75ab18a",
    "corpus_id": 225039882,
    "category": "Computer Science"
  },
  "2010-04159": {
    "title": "Deformable DETR: Deformable Transformers for End-to-End Object Detection",
    "authors": [
      "Xizhou Zhu",
      "Weijie Su",
      "Lewei Lu",
      "Bin Li",
      "Xiaogang Wang",
      "Jifeng Dai"
    ],
    "publication_date": "2020-10-08",
    "venue": "International Conference on Learning Representations",
    "semantic_scholar_id": "39ca8f8ff28cc640e3b41a6bd7814ab85c586504",
    "corpus_id": 222208633,
    "category": "Computer Science"
  },
  "2007-05533": {
    "title": "ISINet: An Instance-Based Approach for Surgical Instrument Segmentation",
    "authors": [
      "Cristina González",
      "Laura Bravo Sánchez",
      "Pablo Arbeláez"
    ],
    "publication_date": "2020-07-10",
    "venue": "International Conference on Medical Image Computing and Computer-Assisted Intervention",
    "semantic_scholar_id": "e9a9ecc79429aaf3fc7848339b0a999bf9ca16f8",
    "corpus_id": 220496042,
    "category": "Computer Science"
  },
  "2007-02501": {
    "title": "Learning Motion Flows for Semi-supervised Instrument Segmentation from Robotic Surgical Video",
    "authors": [
      "Zixu Zhao",
      "Yueming Jin",
      "Xiaojie Gao",
      "Q. Dou",
      "P. Heng"
    ],
    "publication_date": "2020-07-06",
    "venue": "International Conference on Medical Image Computing and Computer-Assisted Intervention",
    "semantic_scholar_id": "434c8edb70cb682691f1c677a18b681edf709e06",
    "corpus_id": 220364003,
    "category": "Computer Science"
  },
  "1912-01703": {
    "title": "PyTorch: An Imperative Style, High-Performance Deep Learning Library",
    "authors": [
      "Adam Paszke",
      "Sam Gross",
      "Francisco Massa",
      "Adam Lerer",
      "James Bradbury",
      "Gregory Chanan",
      "Trevor Killeen",
      "Zeming Lin",
      "N. Gimelshein",
      "L. Antiga",
      "Alban Desmaison",
      "Andreas Köpf",
      "E. Yang",
      "Zachary DeVito",
      "Martin Raison",
      "Alykhan Tejani",
      "Sasank Chilamkurthy",
      "Benoit Steiner",
      "Lu Fang",
      "Junjie Bai",
      "Soumith Chintala"
    ],
    "publication_date": "2019-12-03",
    "venue": "Neural Information Processing Systems",
    "semantic_scholar_id": "3c8a456509e6c0805354bd40a35e3f2dbf8069b1",
    "corpus_id": 202786778,
    "category": "Computer Science, Mathematics"
  },
  "1907-07899": {
    "title": "Incorporating Temporal Prior from Motion Flow for Instrument Segmentation in Minimally Invasive Surgery Video",
    "authors": [
      "Yueming Jin",
      "Keyun Cheng",
      "Q. Dou",
      "P. Heng"
    ],
    "publication_date": "2019-07-18",
    "venue": "International Conference on Medical Image Computing and Computer-Assisted Intervention",
    "semantic_scholar_id": "97d30d02970c9df50f90505c002e616666a9385f",
    "corpus_id": 197544873,
    "category": "Computer Science"
  },
  "1902-06426": {
    "title": "2017 Robotic Instrument Segmentation Challenge",
    "authors": [
      "M. Allan",
      "Alexey A. Shvets",
      "T. Kurmann",
      "Zichen Zhang",
      "Rahul Duggal",
      "Yun-Hsuan Su",
      "Nicola Rieke",
      "Iro Laina",
      "Niveditha Kalavakonda",
      "S. Bodenstedt",
      "Luis C. García-Peraza",
      "Wenqi Li",
      "V. Iglovikov",
      "Huoling Luo",
      "Jian Yang",
      "D. Stoyanov",
      "L. Maier-Hein",
      "S. Speidel",
      "M. Azizian"
    ],
    "publication_date": "2019-02-18",
    "venue": "arXiv.org",
    "semantic_scholar_id": "e705aeaa9440744c8341b14c7404f6a91e694571",
    "corpus_id": 67787647,
    "category": "Computer Science"
  },
  "1803-01207": {
    "title": "Automatic Instrument Segmentation in Robot-Assisted Surgery Using Deep Learning",
    "authors": [
      "Alexey A. Shvets",
      "A. Rakhlin",
      "Alexandr A Kalinin",
      "V. Iglovikov"
    ],
    "publication_date": "2018-03-03",
    "venue": "bioRxiv",
    "semantic_scholar_id": "fd9f5693a34fb839fcc39be83c1835aaee0210e8",
    "corpus_id": 3707841,
    "category": "Computer Science, Biology"
  },
  "1801-08186": {
    "title": "MAttNet: Modular Attention Network for Referring Expression Comprehension",
    "authors": [
      "Licheng Yu",
      "Zhe L. Lin",
      "Xiaohui Shen",
      "Jimei Yang",
      "Xin Lu",
      "Mohit Bansal",
      "Tamara L. Berg"
    ],
    "publication_date": "2018-01-24",
    "venue": "2018 IEEE/CVF Conference on Computer Vision and Pattern Recognition",
    "semantic_scholar_id": "fdce9cbe5c726201575b3c8a8c1af0752f1af53f",
    "corpus_id": 3441497,
    "category": "Computer Science"
  },
  "1801-05746": {
    "title": "TernausNet: U-Net with VGG11 Encoder Pre-Trained on ImageNet for Image Segmentation",
    "authors": [
      "V. Iglovikov",
      "Alexey A. Shvets"
    ],
    "publication_date": "2018-01-17",
    "venue": "Computer-Aided Analysis of Gastrointestinal Videos",
    "semantic_scholar_id": "0269073e07faaafa4df7b3d7ddac96e6dccf853d",
    "corpus_id": 1385457,
    "category": "Computer Science"
  },
  "1703-06870": {
    "title": "Mask R-CNN",
    "authors": [
      "Kaiming He",
      "Georgia Gkioxari",
      "Piotr Dollár",
      "Ross B. Girshick"
    ],
    "publication_date": "2017-03-20",
    "venue": "arXiv reference",
    "semantic_scholar_id": "1a0912bb76777469295bb2c059faee907e7f3258",
    "corpus_id": 54465873,
    "category": "Computer Science"
  },
  "1612-03144": {
    "title": "Feature Pyramid Networks for Object Detection",
    "authors": [
      "Tsung-Yi Lin",
      "Piotr Dollár",
      "Ross B. Girshick",
      "Kaiming He",
      "Bharath Hariharan",
      "Serge J. Belongie"
    ],
    "publication_date": "2016-12-09",
    "venue": "Computer Vision and Pattern Recognition",
    "semantic_scholar_id": "2a94c84383ee3de5e6211d43d16e7de387f68878",
    "corpus_id": 10716717,
    "category": "Computer Science"
  },
  "1505-04597": {
    "title": "U-Net: Convolutional Networks for Biomedical Image Segmentation",
    "authors": [
      "O. Ronneberger",
      "P. Fischer",
      "T. Brox"
    ],
    "publication_date": "2015-05-18",
    "venue": "International Conference on Medical Image Computing and Computer-Assisted Intervention",
    "semantic_scholar_id": "6364fdaa0a0eccd823a779fcdd489173f938e91a",
    "corpus_id": 3719281,
    "category": "Computer Science"
  },
  "2103-14030": {
    "title": "Swin Transformer: Hierarchical Vision Transformer using Shifted Windows",
    "authors": [
      "Ze Liu",
      "Yutong Lin",
      "Yue Cao",
      "Han Hu",
      "Yixuan Wei",
      "Zheng Zhang",
      "Stephen Lin",
      "B. Guo"
    ],
    "publication_date": "",
    "venue": "IEEE International Conference on Computer Vision",
    "semantic_scholar_id": "c8b25fab5608c3e033d34b4483ec47e68ba109b7",
    "corpus_id": 232352874,
    "category": "Computer Science"
  },
  "1810-04805": {
    "title": "BERT: Pre-training of Deep Bidirectional Transformers for Language Understanding",
    "authors": [
      "Jacob Devlin",
      "Ming-Wei Chang",
      "Kenton Lee",
      "Kristina Toutanova"
    ],
    "publication_date": "",
    "venue": "North American Chapter of the Association for Computational Linguistics",
    "semantic_scholar_id": "df2b0e26d0599ce3e70df8a9da02e51594e0e992",
    "corpus_id": 52967399,
    "category": "Computer Science"
  }
}