{
  "2305-11014": {
    "title": "Generalized Planning in PDDL Domains with Pretrained Large Language Models",
    "authors": [
      "Tom Silver",
      "Soham Dan",
      "Kavitha Srinivas",
      "J. Tenenbaum",
      "L. Kaelbling",
      "Michael Katz"
    ],
    "publication_date": "2023-05-18",
    "venue": "AAAI Conference on Artificial Intelligence",
    "semantic_scholar_id": "b3bba15f000000a6d3b5808f798a9fe7629fa499",
    "corpus_id": 258762760,
    "category": "Computer Science"
  },
  "2212-10547": {
    "title": "Semantically-informed Hierarchical Event Modeling",
    "authors": [
      "Shubhashis Roy Dipta",
      "Mehdi Rezaee",
      "Francis Feraro"
    ],
    "publication_date": "2022-12-20",
    "venue": "STARSEM",
    "semantic_scholar_id": "73277209a742e3ae5cf83ed02a28cd011eee045c",
    "corpus_id": 254877737,
    "category": "Computer Science"
  },
  "2210-12485": {
    "title": "DANLI: Deliberative Agent for Following Natural Language Instructions",
    "authors": [
      "Yichi Zhang",
      "Jianing Yang",
      "Jiayi Pan",
      "Shane Storks",
      "N. Devraj",
      "Ziqiao Ma",
      "Keunwoo Peter Yu",
      "Yuwei Bao",
      "J. Chai"
    ],
    "publication_date": "2022-10-22",
    "venue": "Conference on Empirical Methods in Natural Language Processing",
    "semantic_scholar_id": "fc5631cdd08722f51e0ce4b718de0f081ae73603",
    "corpus_id": 253097716,
    "category": "Computer Science"
  },
  "2008-10396": {
    "title": "Design and implementation of a maxi-sized mobile robot (Karo) for rescue missions",
    "authors": [
      "Soheil Habibian",
      "Mehdi Dadvar",
      "Behzad Peykari",
      "Alireza H. M. Hosseini",
      "M. Salehzadeh",
      "Alireza H. M. Hosseini",
      "Farshid Najafi"
    ],
    "publication_date": "2020-07-23",
    "venue": "ROBOMECH Journal",
    "semantic_scholar_id": "d5eff49b997a45ac3b8c176ba629e00142e69674",
    "corpus_id": 221266696,
    "category": "Computer Science"
  },
  "1401-4994": {
    "title": "A review of verbal and non-verbal human-robot interactive communication",
    "authors": [
      "N. Mavridis"
    ],
    "publication_date": "2014-01-20",
    "venue": "Robotics Auton. Syst.",
    "semantic_scholar_id": "5fa3af339964e7b68e5849a22a72211e8a11aa47",
    "corpus_id": 7748652,
    "category": "Computer Science"
  },
  "cs/9906002": {
    "title": "The Symbol Grounding Problem",
    "authors": [
      "S. Harnad"
    ],
    "publication_date": "1990-06-01",
    "venue": "arXiv.org",
    "semantic_scholar_id": "4106342a079eecadd4a4a1d39eabd4a50e0a7cd1",
    "corpus_id": 3204300,
    "category": "Computer Science, Mathematics"
  }
}