{
  "title": "When the Gromov-Hausdorff distance between finite-dimensional space and its subset is finite?",
  "authors": [
    "I. N. Mikhailov",
    "A. A. Tuzhilin"
  ],
  "summary": "In this paper we prove that the Gromov--Hausdorff distance between $\\mathbb{R}^n$ and its subset $A$ is finite if and only if $A$ is an $\\varepsilon$-net in $\\mathbb{R}^n$ for some $\\varepsilon>0$. For infinite-dimensional Euclidean spaces this is not true. The proof is essentially based on upper estimate of the Euclidean Gromov--Hausdorff distance by means of the Gromov-Hausdorff distance.",
  "submission_date": "2024-11-20",
  "revised_dates": [],
  "publication_venue": "arXiv preprint",
  "pdf_url": null,
  "category": "math.MG"
}