{
  "2303-02541": {
    "title": "Continuous Ergodic Capacities",
    "authors": [
      "Yihao Sheng",
      "Yongsheng Song"
    ],
    "publication_date": "2023-03-05",
    "venue": "arXiv reference",
    "semantic_scholar_id": "b5b169c2fc9c666b0baf81bdb563a8ca64f105f7",
    "corpus_id": 257364972,
    "category": "Mathematics"
  },
  "2207-04611": {
    "title": "A strong law of large numbers under sublinear expectations",
    "authors": [
      "Yongsheng Song"
    ],
    "publication_date": "2022-07-11",
    "venue": "Probability, Uncertainty and Quantitative Risk",
    "semantic_scholar_id": "833ae1495016e79f519075e7fe6ba3e2dbde254b",
    "corpus_id": 250426287,
    "category": "Mathematics"
  },
  "2104-08471": {
    "title": "The sufficient and necessary conditions of the strong law of large numbers under the sub-linear expectations",
    "authors": [
      "Li-Xin Zhang"
    ],
    "publication_date": "2021-04-17",
    "venue": "arXiv reference",
    "semantic_scholar_id": "20e9f3f23162b4289ff75bae12453e48a464f195",
    "corpus_id": 266048057,
    "category": "Mathematics"
  },
  "1806-03990": {
    "title": "Ergodicity of invariant capacities",
    "authors": [
      "Chunrong Feng",
      "Panyu Wu",
      "Huaizhong Zhao"
    ],
    "publication_date": "2018-06-11",
    "venue": "arXiv reference",
    "semantic_scholar_id": "01e2edc94a87126b8e88f189c1ab6aa8b74f13ec",
    "corpus_id": 119152059,
    "category": "Mathematics"
  },
  "1705-03549": {
    "title": "Ergodicity of Sublinear Markovian Semigroups",
    "authors": [
      "Chunrong Feng",
      "Huaizhong Zhao"
    ],
    "publication_date": "2017-05-09",
    "venue": "SIAM Journal on Mathematical Analysis",
    "semantic_scholar_id": "caf3367680cf80ad59b1d48e51513e3814e3e001",
    "corpus_id": 235829219,
    "category": "Mathematics, Computer Science"
  },
  "1511-05631": {
    "title": "Two laws of large numbers for sublinear expectations",
    "authors": [
      "Wenhao Li",
      "Chuanfeng Sun"
    ],
    "publication_date": "2015-11-18",
    "venue": "arXiv reference",
    "semantic_scholar_id": "45e622b01d87110f640f495a46a0e93ff2d9ebe4",
    "corpus_id": 73664183,
    "category": "Mathematics"
  },
  "1508-01329": {
    "title": "Ergodic Theorems for lower probabilities",
    "authors": [
      "S. Cerreia-Vioglio",
      "F. Maccheroni",
      "M. Marinacci"
    ],
    "publication_date": "2015-08-06",
    "venue": "arXiv reference",
    "semantic_scholar_id": "18d048c32bef1ba8c34413acf62b274aa9271981",
    "corpus_id": 54843575,
    "category": "Mathematics"
  },
  "0803-2656": {
    "title": "A New Central Limit Theorem under Sublinear Expectations",
    "authors": [
      "S. Peng"
    ],
    "publication_date": "2008-03-18",
    "venue": "arXiv reference",
    "semantic_scholar_id": "cae50479c151c483e0316ccf8c0708c3ec52a870",
    "corpus_id": 15546914,
    "category": "Mathematics"
  }
}